hivemind_nfc_reader.py
hivemind_nfc_reader-0.4.5.dist-info/entry_points.txt
hivemind_nfc_reader-0.4.5.dist-info/LICENSE
hivemind_nfc_reader-0.4.5.dist-info/WHEEL
hivemind_nfc_reader-0.4.5.dist-info/METADATA
hivemind_nfc_reader-0.4.5.dist-info/RECORD
