Metadata-Version: 2.1
Name: hivemind_nfc_reader
Version: 0.4.5
Summary: HiveMind NFC reader client
Author-email: KQHiveMind <contact@kqhivemind.com>
Classifier: License :: OSI Approved :: MIT License
Requires-Dist: requests==2.31.0
Requires-Dist: gpiozero==1.6.2
Requires-Dist: websocket-client==1.2.1
Requires-Dist: nfcpy==1.0.3
Requires-Dist: py532lib==2018.6.14.dev1
Project-URL: Home, https://kqhivemind.com
